simple_progress_bar.py
simple_progress_bar-0.0.5.dist-info/LICENSE
simple_progress_bar-0.0.5.dist-info/METADATA
simple_progress_bar-0.0.5.dist-info/WHEEL
simple_progress_bar-0.0.5.dist-info/top_level.txt
simple_progress_bar-0.0.5.dist-info/RECORD
