Metadata-Version: 2.1
Name: simple-progress-bar
Version: 0.0.5
Summary: Simple progress bar for your console apps in python
Home-page: https://github.com/mLandim/simple_progress_bar
Author: Marcelo Landim
Author-email: marcelolandim85@gmail.com
License: MIT
Project-URL: Bug Report, https://github.com/mLandim/simple_progress_bar/issues
Keywords: progress,bar,progress-bar,console,terminal
Platform: UNKNOWN
Classifier: Development Status :: 3 - Alpha
Classifier: Intended Audience :: Developers
Classifier: Topic :: Software Development :: Build Tools
Classifier: License :: OSI Approved :: MIT License
Classifier: Programming Language :: Python :: 3
Classifier: Programming Language :: Python :: 3.6
Classifier: Programming Language :: Python :: 3.7
Classifier: Operating System :: OS Independent
Requires-Python: >=3.6
Provides-Extra: dev
Requires-Dist: tox (>=3.24) ; extra == 'dev'
Requires-Dist: check-manifest (>=0.47wheel) ; extra == 'dev'
